pyqart/__init__.py
pyqart/qart_entry.py
pyqart/qr_entry.py
pyqart/art/__init__.py
pyqart/art/bitblock.py
pyqart/art/exception.py
pyqart/art/qart.py
pyqart/art/source.py
pyqart/art/target.py
pyqart/common/__init__.py
pyqart/common/bit_funcs.py
pyqart/common/bits.py
pyqart/common/exception.py
pyqart/qr/__init__.py
pyqart/qr/exception.py
pyqart/qr/args/__init__.py
pyqart/qr/args/args.py
pyqart/qr/args/mask.py
pyqart/qr/args/rotation.py
pyqart/qr/args/version.py
pyqart/qr/data/__init__.py
pyqart/qr/data/alphanumeric.py
pyqart/qr/data/base.py
pyqart/qr/data/data.py
pyqart/qr/data/exception.py
pyqart/qr/data/numbers.py
pyqart/qr/data/raw.py
pyqart/qr/ec/__init__.py
pyqart/qr/ec/gf.py
pyqart/qr/ec/poly.py
pyqart/qr/ec/rsencoder.py
pyqart/qr/painter/__init__.py
pyqart/qr/painter/canvas.py
pyqart/qr/painter/exception.py
pyqart/qr/painter/painter.py
pyqart/qr/painter/point.py
pyqart/qr/printer/__init__.py
pyqart/qr/printer/base.py
pyqart/qr/printer/halftone_printer.py
pyqart/qr/printer/image_printer.py
pyqart/qr/printer/string_printer.py
pyqart-0.1.0.dist-info/DESCRIPTION.rst
pyqart-0.1.0.dist-info/METADATA
pyqart-0.1.0.dist-info/RECORD
pyqart-0.1.0.dist-info/WHEEL
pyqart-0.1.0.dist-info/entry_points.txt
pyqart-0.1.0.dist-info/metadata.json
pyqart-0.1.0.dist-info/top_level.txt
test/__init__.py
test/test_alphanumeric.py
test/test_bits.py
test/test_bits_utils.py
test/test_encode_numbers.py
test/test_encode_raw.py
